searchadscli/__init__.py
searchadscli/commands/__init__.py
searchadscli/commands/campaign.py
searchadscli/commands/configure.py
searchadscli/commands/keywords.py
searchadscli/main.py
searchadscli/utils/__init__.py
searchadscli/utils/access_token.py
searchadscli/utils/adgroups_api.py
searchadscli/utils/campaigns_api.py
searchadscli/utils/config.py
searchadscli/utils/keywords_api.py
searchadscli-0.1.0.dist-info/METADATA
searchadscli-0.1.0.dist-info/WHEEL
searchadscli-0.1.0.dist-info/entry_points.txt
searchadscli-0.1.0.dist-info/RECORD
