Metadata-Version: 2.1
Name: searchadscli
Version: 0.1.0
Summary: A CLI for running Apple Search Ads Advanced campaigns.
Author: rkotzy
Author-email: yolo@ryan.wtf
Requires-Python: >=3.11,<4.0
Classifier: Programming Language :: Python :: 3
Classifier: Programming Language :: Python :: 3.11
Requires-Dist: authlib (>=1.2.1,<2.0.0)
Requires-Dist: pycryptodome (>=3.18.0,<4.0.0)
Requires-Dist: requests (>=2.31.0,<3.0.0)
Requires-Dist: typer[all] (>=0.9.0,<0.10.0)
